[
  {
    "type": 0,
    "title": "醫學院學生壓力及學習生活意見調查",
    "description": "Survey on the Stress Level and Learning Experience of CUHK Medical Students",
    "required": true
  },
  {
    "type": 4,
    "title": "你覺得此刻的壓力指數是(1-7)?",
    "description": "What is your current level of stress, on a scale of 1-7?",
    "default": null,
    "likert-max": "最小 Lowest",
    "likert-min": "最大 Highest",
    "required": true
  },
  {
    "type": 5,
    "title": "你的壓力主要來自？(可選多於一項) What is the main source of your stress? (You may choose more than one option.)",
    "default": null,
    "choices": [
      "學業 Academic",
      "家人 Family",
      "自己的期望 Expectations towards self",
      "感情 Relationship",
      "金錢 Money",
      "課外活動 Extra-curricular activities"
    ],
    "others": true,
    "required": true
  },
  {
    
    "type": 3,
    "title": "你平均每星期花多少時間溫習？How much time do you spend on revision every week?",
    "default": null,
    "choices": [
      "<10 hours",
      "11-20 hours",
      "21-30 hours",
      "31-40 hours",
      "41-50 hours",
      ">51 hours"
    ],
    "required": true
  },
  {
    "type": 4,
    "title": "你覺得在考試前夕(一個月內)的壓力指數平均是？",
    "description": "What is your AVERAGE level of stress in the month before exams?",
    "default": null,
    "likert-max": "最小 Lowest",
    "likert-min": "最大 Highest",
    "required": true
  },
  {
    "type": 4,
    "title": "你覺得在考試前夕(一個月內)的壓力指數最大是？",
    "description": "What is your MAXIMUM level of stress in the month before exams?",
    "default": null,
    "likert-max": "最小 Lowest",
    "likert-min": "最大 Highest",
    "required": true
  },
  {
    "type": 1,
    "title": "承上題，何時壓力最大？",
    "description": "Further to the above question, when did you feel the most stressed?",
    "required": true
  },
  {
    "type": 4,
    "title": "你有多擔心自己考試不合格？",
    "description": "How worried are you about failing the exam? ",
    "default": null,
    "likert-max": "非常擔心 Extremely worried",
    "likert-min": "不擔心 Not worried",
    "required": true
  },
  {
    "type": 5,
    "title": "你感到有壓力時會與何人分擔？(可選多於一項) ",
    "description": "Who would you share your feelings with when you feel stressed? (You may choose more than one option.)",
    "default": null,
    "choices": [
      "家人 Family",
      "朋友 Friends",
      "男/女朋友 Boyfriend/Girlfriend",
      "同學 Classmates",
      "老師 Teacher",
      "社工 Social worker",
      "心理輔導員 Counsellor"
    ],
    "others": true,
    "required": true
  },
  {
    "type": 5,
    "title": "你感到有壓力時會與何人分擔？(可選多於一項) ",
    "description": "Who would you share your feelings with when you feel stressed? (You may choose more than one option.)",
    "default": null,
    "choices": [
      "家人 Family",
      "朋友 Friends",
      "男/女朋友 Boyfriend/Girlfriend",
      "同學 Classmates",
      "老師 Teacher",
      "社工 Social worker",
      "心理輔導員 Counsellor"
    ],
    "others": true,
    "required": true
  },
  {
    "type": 5,
    "title": "你會如何減壓？(可選多於一項)",
    "description": "How do you relieve your stress? (You may choose more than one option.)",
    "default": null,
    "choices": [

"做運動 Exercise",
"打機 Play computer games",
"購物 Go shopping",
"進食 Eat",
"睡覺 Sleep",
"與人聊天 Chat with someone",
"聽歌 Listen to music"
    ],
    "others": true,
    "required": true
  },
  {
    "type": 4,
    "title": "你有多滿意現在的教學模式？(1-7)",
    "description": "How satisfied are you, on a scale of 1-7, with the current mode of teaching and learning?",
    "default": null,
    "likert-max": "最滿意 Most",
    "likert-min": "最不滿意 Least",
    "required": true
  },
  {
    "type": 3,
    "title": "你是否直接入讀Year 2? Did you directly enter Year 2?",
    "default": null,
    "choices": [
      "Yes (Postgraduate)",
      "Yes (Transfer)",
      "Yes (GPS)",
      "No"
    ],
    "required": true
  },
  {
    "type": 1,
    "title": "姓名 Name (Optional)",
    "description": "All answers you provided above will be kept anonymous and confidential. The sole purpose of collecting your name is for us to follow up on your thoughts/suggestions if necessary. You may feel free to leave this blank too :)",
    "required": true
  }
]
